prisma/__init__.py
prisma/__main__.py
prisma/_async_http.py
prisma/_base_client.py
prisma/_builder.py
prisma/_compat.py
prisma/_config.py
prisma/_constants.py
prisma/_fields.py
prisma/_metrics.py
prisma/_proxy.py
prisma/_raw_query.py
prisma/_registry.py
prisma/_sync_http.py
prisma/_transactions.py
prisma/_types.py
prisma/_typing.py
prisma/errors.py
prisma/fields.py
prisma/http_abstract.py
prisma/mypy.py
prisma/py.typed
prisma/testing.py
prisma/utils.py
prisma/validator.py
prisma/_vendor/__init__.py
prisma/_vendor/lark_schema_parser.py
prisma/_vendor/lark_schema_scan_parser.py
prisma/binaries/__init__.py
prisma/binaries/constants.py
prisma/binaries/platform.py
prisma/cli/__init__.py
prisma/cli/_node.py
prisma/cli/cli.py
prisma/cli/custom.py
prisma/cli/options.py
prisma/cli/prisma.py
prisma/cli/utils.py
prisma/cli/commands/__init__.py
prisma/cli/commands/dev.py
prisma/cli/commands/fetch.py
prisma/cli/commands/generate.py
prisma/cli/commands/version.py
prisma/engine/__init__.py
prisma/engine/_abstract.py
prisma/engine/_http.py
prisma/engine/_query.py
prisma/engine/errors.py
prisma/engine/utils.py
prisma/generator/__init__.py
prisma/generator/errors.py
prisma/generator/filters.py
prisma/generator/generator.py
prisma/generator/jsonrpc.py
prisma/generator/models.py
prisma/generator/schema.py
prisma/generator/types.py
prisma/generator/utils.py
prisma/generator/_dsl_parser/__init__.py
prisma/generator/_dsl_parser/parser.py
prisma/generator/_dsl_parser/transformer.py
prisma/generator/templates/_header.py.jinja
prisma/generator/templates/_pragma.py.jinja
prisma/generator/templates/_utils.py.jinja
prisma/generator/templates/actions.py.jinja
prisma/generator/templates/bases.py.jinja
prisma/generator/templates/client.py.jinja
prisma/generator/templates/enums.py.jinja
prisma/generator/templates/http.py.jinja
prisma/generator/templates/metadata.py.jinja
prisma/generator/templates/models.py.jinja
prisma/generator/templates/partials.py.jinja
prisma-0.14.0.dist-info/LICENSE
prisma-0.14.0.dist-info/METADATA
prisma-0.14.0.dist-info/WHEEL
prisma-0.14.0.dist-info/entry_points.txt
prisma-0.14.0.dist-info/top_level.txt
prisma-0.14.0.dist-info/RECORD
