Metadata-Version: 2.1
Name: prisma
Version: 0.14.0
Summary: Prisma Client Python is an auto-generated and fully type-safe database client
Home-page: https://github.com/RobertCraigie/prisma-client-py
Author: Robert Craigie
Author-email: robert@craigie.dev
Maintainer: Robert Craigie
License: APACHE
Project-URL: Documentation, https://prisma-client-py.readthedocs.io
Project-URL: Source, https://github.com/RobertCraigie/prisma-client-py
Project-URL: Tracker, https://github.com/RobertCraigie/prisma-client-py/issues
Keywords: orm,mysql,typing,prisma,sqlite,database,postgresql
Platform: UNKNOWN
Classifier: Development Status :: 4 - Beta
Classifier: Intended Audience :: Developers
Classifier: Typing :: Typed
Classifier: Topic :: Software Development :: Libraries :: Python Modules
Classifier: Topic :: Database :: Database Engines/Servers
Classifier: Topic :: Database :: Front-Ends
Classifier: License :: OSI Approved :: Apache Software License
Classifier: Programming Language :: Python :: 3.8
Classifier: Programming Language :: Python :: 3.9
Classifier: Programming Language :: Python :: 3.10
Classifier: Programming Language :: Python :: 3.11
Classifier: Programming Language :: Python :: 3.12
Classifier: Operating System :: POSIX
Classifier: Operating System :: MacOS
Classifier: Operating System :: POSIX :: Linux
Classifier: Operating System :: Microsoft :: Windows
Requires-Python: >=3.8.0
Provides-Extra: node
Provides-Extra: all
License-File: LICENSE
